bida/__init__.py
bida/config.py
bida/util.py
bida/core/__init__.py
bida/core/conversation.py
bida/core/conversation_buffer.py
bida/core/embedding_api_base.py
bida/core/embedding_operator.py
bida/core/llm_api_base.py
bida/core/llm_chat_operator.py
bida/core/llm_operator.py
bida/core/llm_text_operator.py
bida/core/management_functions.py
bida/core/management_models.py
bida/core/model_api_base.py
bida/core/model_operator_base.py
bida/core/prompt_template_base.py
bida/core/prompt_template_text.py
bida/functions/README.md
bida/functions/__init__.py
bida/functions/_json_template.json
bida/functions/get_weather.json
bida/functions/get_weather.py
bida/functions/search_web.json
bida/functions/search_web.py
bida/models/README.md
bida/models/__init__.py
bida/models/_json_template.json
bida/models/aliyun.json
bida/models/aliyun_api.py
bida/models/baichuan.json
bida/models/baichuan_api.py
bida/models/baichuan_sdk.py
bida/models/baidu.json
bida/models/baidu_api.py
bida/models/baidu_sdk.py
bida/models/baidu_thirdmodels.json
bida/models/baidu_thirdmodels_api.py
bida/models/chatglm.json
bida/models/chatglm_api.py
bida/models/minimax.json
bida/models/minimax_api.py
bida/models/minimax_pro.json
bida/models/minimax_pro_api.py
bida/models/minimax_sdk.py
bida/models/openai.json
bida/models/openai_api.py
bida/models/sensetime.json
bida/models/sensetime_api.py
bida/models/tencent.json
bida/models/tencent_api.py
bida/models/tencent_sdk.py
bida/models/xfyun.json
bida/models/xfyun_api.py
bida/models/xfyun_sdk.py
bida-0.9.4.dist-info/LICENSE
bida-0.9.4.dist-info/METADATA
bida-0.9.4.dist-info/WHEEL
bida-0.9.4.dist-info/top_level.txt
bida-0.9.4.dist-info/RECORD
