Metadata-Version: 2.1
Name: bida
Version: 0.9.4
Summary: bida， 简单、易用、稳定、高效，便于扩展和集成的，大语言模型工程化开发框架
Home-page: https://github.com/pfzhou/bida
Author: Pengfei Zhou
Author-email: pfzhou@gmail.com
Keywords: ai aigc llm chat completion embedding
Classifier: Programming Language :: Python :: 3
Classifier: License :: OSI Approved :: MIT License
Classifier: Operating System :: OS Independent
Requires-Python: >=3.9
License-File: LICENSE
Requires-Dist: duckdb (==0.8.1)
Requires-Dist: pydantic (==1.10.8)
Requires-Dist: python-dotenv (==1.0.0)
Requires-Dist: requests (==2.31.0)
Requires-Dist: websocket-client (==1.6.1)
Requires-Dist: sseclient-py (==1.7.2)
Requires-Dist: openai (==0.27.7)
Requires-Dist: tiktoken (==0.4.0)
Requires-Dist: dashscope (==1.9.0)
Requires-Dist: zhipuai (==1.0.7)
Requires-Dist: sensenova (==1.0.5)
